Metadata-Version: 1.1
Name: scihub2pdf
Version: 0.4.1
Summary: Downloads pdfs via a DOI number(or arxivId), article title or a bibtex file, sci-hub
Home-page: https://github.com/bibcure/scihub2pdf
Author: Bruno Messias
Author-email: messias.physics@gmail.com
License: AGPLv3
Download-URL: https://github.com/bibcure/scihub2pdf/archive/0.4.1.tar.gz
Keywords: bibtex,sci-hub,libgen,doi,science,scientific-journals
Platform: UNKNOWN
Classifier: License :: OSI Approved :: GNU Affero General Public License v3 or later (AGPLv3+)
Classifier: Intended Audience :: Science/Research
Classifier: Programming Language :: Python
Classifier: Topic :: Text Processing :: Markup :: LaTeX
